Ego-ST
calibration_camera
dual_luci_capture
examples
luci
navigation_task
sdk_capture
sdk_memory
sdk_save_video
setup_connection
testenv
