Metadata-Version: 2.4
Name: luci-sdk
Version: 0.1.1
Summary: Python SDK for the LUCI Pin device
Author-email: Memories AI Labs <contact@memories-ai.com>
License: MIT
Project-URL: homepage, https://github.com/Memories-ai-labs/luci_sdk
Requires-Python: >=3.9
License-File: LICENSE
Requires-Dist: opencv-python
Requires-Dist: Pillow
Requires-Dist: pyserial
Requires-Dist: ffmpeg-python
Dynamic: license-file
